LICENSE
README.md
setup.py
delugeonal/__init__.py
delugeonal/delugeonal.py
delugeonal/mediadb.py
delugeonal/mediaserver.py
delugeonal/mediasite.py
delugeonal/torrent.py
delugeonal/torrentclient.py
delugeonal.egg-info/PKG-INFO
delugeonal.egg-info/SOURCES.txt
delugeonal.egg-info/dependency_links.txt
delugeonal.egg-info/entry_points.txt
delugeonal.egg-info/requires.txt
delugeonal.egg-info/top_level.txt
delugeonal/clients/__init__.py
delugeonal/clients/deluge.py
delugeonal/clients/transmission.py
delugeonal/dbs/__init__.py
delugeonal/dbs/imdb.py
delugeonal/dbs/thetvdb.py
delugeonal/servers/__init__.py
delugeonal/servers/plex.py
delugeonal/sites/__init__.py
delugeonal/sites/eztv.py
delugeonal/sites/ipt.py
delugeonal/sites/tgx.py
delugeonal/sites/torrenting.py