Metadata-Version: 2.1
Name: delugeonal
Version: 0.0.13
Summary: Automate and control multiple aspects of a torrent/media infrastructure.
Home-page: https://github.com/pgillan145/delugeonal
Author: Patrick Gillan
Author-email: pgillan@minorimpact.com
License: GPLv3
Classifier: Development Status :: 2 - Pre-Alpha
Classifier: Environment :: Console
Classifier: License :: OSI Approved :: GNU General Public License v3 (GPLv3)
Classifier: Natural Language :: English
Classifier: Operating System :: POSIX
Classifier: Programming Language :: Python :: 3
Classifier: Topic :: Utilities
License-File: LICENSE
